{
  "id": "2018-09-14_california-independent-system-operator-corporati_pa17-3",
  "company": "California Independent System Operator Corporation",
  "company_raw": "PA17-3 California Independent System Operator Corporation",
  "docket": "PA17-3",
  "docket_full": "PA17-3-000",
  "issued_date": "2018-09-14",
  "source_page_url": "https://elibrary.ferc.gov/eLibrary/filelist?accession_number=20180914-3005&optimized=false",
  "pdf_download_url": "https://elibrary.ferc.gov/eLibraryWebAPI/api/File/DownloadPDF?accesssionNumber=20180914-3005",
  "captured_at": "2021-12-07",
  "source_note": "Listed on FERC ferc.gov/audits via Internet Archive Wayback Machine (snapshot 2021-12-07; origin www.ferc.gov); report PDF from FERC eLibrary, accession 20180914-3005 (fileID 15038664).",
  "archived_via": "https://web.archive.org/web/20211207020015/https://www.ferc.gov/audits",
  "page_count": 62,
  "scanned_pages": [],
  "ocr_used": false,
  "audit_period": "January 1, 2014 to the March 2, 2018",
  "industry": "electric",
  "audit_type": "non-financial",
  "functions": [
    "generation",
    "transmission"
  ],
  "forms": [
    "1"
  ],
  "finding_count": 0,
  "findings": []
}