{
  "collection": "prudence_review",
  "jurisdiction": "FERC",
  "source": "FERC (eLibrary)",
  "doc_type": "Commission opinion on initial decision",
  "id": "2017-01-19_potomac-appalachian-transmission-highline_er12-2708-opinion-554",
  "company": "Potomac-Appalachian Transmission Highline, LLC and PJM Interconnection, L.L.C.",
  "company_raw": "Potomac-Appalachian Transmission Highline, LLC and PJM Interconnection, L.L.C.",
  "docket": "ER12-2708",
  "docket_full": null,
  "issued_date": "2017-01-19",
  "source_page_url": "https://elibrary.ferc.gov/eLibrary/filelist?accession_number=20170119-3062&optimized=false",
  "pdf_download_url": "https://elibrary.ferc.gov/eLibraryWebAPI/api/File/DownloadPDF?accesssionNumber=20170119-3062",
  "captured_at": "2026-06-02",
  "source_note": "FERC Opinion No. 554, Order on Initial Decision, on the prudence of the Potomac-Appalachian Transmission Highline (PATH) project's transmission abandonment cost claim (formal challenges, ROE, and legal/advertising/lobbying costs) — affirming in part and reversing in part the ALJ initial decision. Potomac-Appalachian Transmission Highline, LLC and PJM, Dockets ER12-2708 / ER09-1256, issued January 19, 2017 (158 FERC para. 61,050). Distinct from the 2015 ALJ initial decision already in this collection. Found via the eLibrary AdvancedSearch API; accession 20170119-3062.",
  "archived_via": null,
  "page_count": 124,
  "scanned_pages": [],
  "ocr_used": false,
  "audit_period": null,
  "industry": "electric",
  "audit_type": null,
  "functions": [],
  "forms": [],
  "finding_count": 0,
  "findings": [],
  "structured": false
}