{
  "collection": "state_audit",
  "jurisdiction": "NY",
  "source": "New York State Department of Public Service",
  "doc_type": "rate case summary",
  "id": "2025-07_nyseg_ny-25-e-0375-rate-case-summary",
  "company": "New York State Electric & Gas Corporation",
  "company_raw": "New York State Electric & Gas Corporation",
  "docket": "25-E-0375",
  "docket_full": null,
  "issued_date": null,
  "source_page_url": "https://dps.ny.gov/pending-and-recent-electric-rate-cases",
  "pdf_download_url": "https://dps.ny.gov/system/files/documents/2025/07/nyseg-electric-rate-case-25-e-0375.pdf",
  "captured_at": "2026-06-07",
  "source_note": "New York DPS electric rate-case summary for New York State Electric & Gas Corporation (NYSEG), Case 25-E-0375 — published under Public Service Law §66(12)(l). NYSEG's June 30, 2025 filing requested an increase in annual electric revenues of ~$464.4M (35.0% to delivery revenues) for the rate year ending April 30, 2027. Listed for reference (metadata-only). Source: NY DPS (dps.ny.gov/system/files/documents/2025/07/nyseg-electric-rate-case-25-e-0375.pdf).",
  "archived_via": null,
  "page_count": 1,
  "scanned_pages": [],
  "ocr_used": false,
  "audit_period": null,
  "industry": "electric",
  "audit_type": null,
  "functions": [],
  "forms": [],
  "finding_count": 0,
  "findings": [],
  "structured": false
}