{
  "collection": "state_audit",
  "jurisdiction": "MS",
  "source": "Public Service Commission",
  "doc_type": null,
  "id": "ms_0000_001_report-lack-of-service",
  "company": "Report Lack of Service",
  "company_raw": "Report Lack of Service",
  "docket": null,
  "docket_full": null,
  "issued_date": null,
  "source_page_url": "https://www.psc.state.ms.us",
  "pdf_download_url": "https://www.psc.state.ms.us/ztg/home",
  "captured_at": "2026-06-14",
  "source_note": "Public Service Commission (MS)",
  "archived_via": null,
  "page_count": 0,
  "scanned_pages": [],
  "ocr_used": false,
  "audit_period": null,
  "industry": null,
  "audit_type": null,
  "functions": [],
  "forms": [],
  "finding_count": 0,
  "findings": [],
  "structured": false
}