{"collection": "state_rate_case", "jurisdiction": "MO", "source": "Missouri Public Service Commission", "doc_type": "order", "id": "eo-2022-0027_union-electric-ameren-missouri_mo-commission-order-fac-truup-far", "company": "Union Electric Company d/b/a Ameren Missouri", "company_raw": "Union Electric Company d/b/a Ameren Missouri", "docket": "EO-2022-0027", "docket_full": null, "issued_date": null, "source_page_url": "https://efis.psc.mo.gov/Document/Display/80659", "pdf_download_url": "https://efis.psc.mo.gov/Document/Display/80659", "captured_at": "2026-06-02", "source_note": "Order of the Missouri Public Service Commission (session order) addressing Union Electric Company d/b/a Ameren Missouri's Fuel Adjustment Clause true-up (File No. EO-2022-0027), Fuel Adjustment Rate adjustment (File No. ER-2022-0026), and related rate proceeding (ER-2021-0240) (15 pp). Listed for reference (metadata-only). Source: Missouri PSC EFIS, document 80659 (efis.psc.mo.gov/Document/Display/80659).", "archived_via": null, "page_count": 15, "scanned_pages": [], "ocr_used": false, "audit_period": null, "industry": "electric", "audit_type": null, "functions": [], "forms": [], "finding_count": 0, "findings": [], "structured": false}