{
  "collection": "state_audit",
  "jurisdiction": "GA",
  "source": "Public Service Commission",
  "doc_type": null,
  "id": "ga_0000_000_gufpa-violation-reporting-system",
  "company": "GUFPA Violation Reporting System",
  "company_raw": "GUFPA Violation Reporting System",
  "docket": null,
  "docket_full": null,
  "issued_date": null,
  "source_page_url": "https://www.psc.state.ga.us",
  "pdf_download_url": "http://gufpa.psc.state.ga.us/",
  "captured_at": "2026-06-14",
  "source_note": "Public Service Commission (GA)",
  "archived_via": null,
  "page_count": 0,
  "scanned_pages": [],
  "ocr_used": false,
  "audit_period": null,
  "industry": null,
  "audit_type": null,
  "functions": [],
  "forms": [],
  "finding_count": 0,
  "findings": [],
  "structured": false
}